MANIFEST.in
setup.py
bin/execconf
execconf/__init__.py
execconf/__main__.py
execconf/builder.py
execconf/config.py
execconf/exceptions.py
execconf/helpers.py
execconf/loader.py
execconf/utils.py
execconf.egg-info/PKG-INFO
execconf.egg-info/SOURCES.txt
execconf.egg-info/dependency_links.txt
execconf.egg-info/top_level.txt
execconf/tests/__init__.py
execconf/tests/__main__.py
execconf/tests/data_defaults.py
execconf/tests/test_builder.py
execconf/tests/test_config.py
execconf/tests/test_loader.py
execconf/tests/test_utils.py
execconf/tests/test_validator.py
execconf/tests/test_validator_nodes.py
execconf/tests/data/base.py
execconf/tests/data/base2.py
execconf/tests/data/complex_helpers-include.py
execconf/tests/data/complex_helpers-merge.py
execconf/tests/data/complex_helpers-merge_option.py
execconf/tests/data/complex_helpers.py
execconf/tests/data/deepload.py
execconf/tests/data/deepload_except.py
execconf/tests/data/deepload_except1.py
execconf/tests/data/deepload_include1.py
execconf/tests/data/deepload_include2.py
execconf/tests/data/deepload_include6.py
execconf/tests/data/default.py
execconf/tests/data/except_abspath.py
execconf/tests/data/exts.txt
execconf/tests/data/exts_except.txt
execconf/tests/data/exts_exists.py
execconf/tests/data/exts_exists.txt
execconf/tests/data/exts_md.md
execconf/tests/data/exts_prior.js
execconf/tests/data/exts_prior.py
execconf/tests/data/filter.py
execconf/tests/data/include.py
execconf/tests/data/include_merge.py
execconf/tests/data/merge-merging.py
execconf/tests/data/merge.py
execconf/tests/data/merge_option-merging.py
execconf/tests/data/merge_option-merging2.py
execconf/tests/data/merge_option.py
execconf/tests/data/no_replacement.py
execconf/tests/data/replacement.py
execconf/tests/data/deepload/deepload_include3.py
execconf/tests/data/deepload/deepload_include5.py
execconf/tests/data/deepload/moredeep/deepload_include4.py
execconf/tests/data/validator/simple_config.py
execconf/tests/data/validator/simple_config.validate.py
execconf/validator/__init__.py
execconf/validator/nodes.py