Metadata-Version: 1.1
Name: execconf
Version: 0.3.5
Summary: Executable config on pure python
Home-page: https://github.com/DriverX/execconf
Author: Anton Ilyushenkov
Author-email: me@driverx.ru
License: http://opensource.org/licenses/MIT
Platform: UNKNOWN
Classifier: License :: OSI Approved :: MIT License
Classifier: Programming Language :: Python
Classifier: Programming Language :: Python :: 2.7
Classifier: Development Status :: 5 - Production/Stable
Classifier: Intended Audience :: Developers
Classifier: Intended Audience :: System Administrators
Classifier: Operating System :: Unix
Classifier: Topic :: Utilities
